[22,"ItemInHandColor","",{"Fancy":["Off","On"],"Instancing":["Off","On"],"MultiColorTint":["Off","On"]},[["color0",3,4,0,0,-1,-1],["fog",3,4,2,0,-1,-1],["instanceData0",3,7,7,1,-1,-1],["instanceData1",3,7,6,1,-1,-1],["instanceData2",3,7,5,1,-1,-1],["light",3,4,1,0,-1,-1],["normal",3,1,0,0,-1,-1],["position",2,0,0,0,-1,-1],["texcoord0",1,7,0,0,-1,-1],["worldPos",2,7,3,0,-1,-1]],[],[["ChangeColor",2,1,[1.0,1.0,1.0,1.0]],["ColorBased",2,1,[1.0,1.0,1.0,1.0]],["FogColor",2,1,[1.0,1.0,1.0,0.0]],["FogControl",2,1,[0.0,0.0,0.0,0.0]],["LightDiffuseColorAndIlluminance",2,1,[1.0,1.0,1.0,1.0]],["LightWorldSpaceDirection",2,1,[0.0,-1.0,0.0,1.0]],["MaterialID",2,1,[0.0,0.0,0.0,0.0]],["MultiplicativeTintColor",2,1,[1.0,1.0,1.0,1.0]],["OverlayColor",2,1,[1.0,1.0,1.0,0.0]],["SubPixelOffset",2,1,[0.0,0.0,0.0,0.0]],["TileLightColor",2,1,[1.0,1.0,1.0,1.0]],["TileLightIntensity",2,1,[0.0,0.0,0.0,0.0]]],[["AlphaTest","111111111111111","","",{"0":0,"1":0,"2":0},[[1,{"0":0,"1":0,"2":0},[[0,8,[0,2,3,4,6,7,8]],[1,9,[0,1,5,8,9]],[1,8,[0,1,5,8,9]],[0,9,[0,2,3,4,6,7,8]]]],[1,{"0":0,"1":0,"2":1},[[0,8,[0,2,3,4,6,7,8]],[1,9,[0,1,5,8,9]],[1,8,[0,1,5,8,9]],[0,9,[0,2,3,4,6,7,8]]]],[1,{"0":0,"1":1,"2":0},[[0,8,[0,2,3,4,6,7,8]],[1,9,[0,1,5,8,9]],[1,8,[0,1,5,8,9]],[0,9,[0,2,3,4,6,7,8]]]],[1,{"0":0,"1":1,"2":1},[[0,8,[0,2,3,4,6,7,8]],[1,9,[0,1,5,8,9]],[1,8,[0,1,5,8,9]],[0,9,[0,2,3,4,6,7,8]]]],[1,{"0":1,"1":0,"2":0},[[0,8,[0,2,3,4,6,7,8]],[1,9,[0,1,5,8,9]],[1,8,[0,1,5,8,9]],[0,9,[0,2,3,4,6,7,8]]]],[1,{"0":1,"1":0,"2":1},[[0,8,[0,2,3,4,6,7,8]],[1,9,[0,1,5,8,9]],[1,8,[0,1,5,8,9]],[0,9,[0,2,3,4,6,7,8]]]],[1,{"0":1,"1":1,"2":0},[[0,8,[0,2,3,4,6,7,8]],[1,9,[0,1,5,8,9]],[1,8,[0,1,5,8,9]],[0,9,[0,2,3,4,6,7,8]]]],[1,{"0":1,"1":1,"2":1},[[0,8,[0,2,3,4,6,7,8]],[1,9,[0,1,5,8,9]],[1,8,[0,1,5,8,9]],[0,9,[0,2,3,4,6,7,8]]]]]],["DepthOnly","111111111111111","","",{"0":0,"1":0,"2":0},[[1,{"0":0,"1":0,"2":0},[[0,8,[0,2,3,4,6,7,8]],[1,9,[0,1,5,8,9]],[1,8,[0,1,5,8,9]],[0,9,[0,2,3,4,6,7,8]]]],[1,{"0":0,"1":0,"2":1},[[0,8,[0,2,3,4,6,7,8]],[1,9,[0,1,5,8,9]],[1,8,[0,1,5,8,9]],[0,9,[0,2,3,4,6,7,8]]]],[1,{"0":0,"1":1,"2":0},[[0,8,[0,2,3,4,6,7,8]],[1,9,[0,1,5,8,9]],[1,8,[0,1,5,8,9]],[0,9,[0,2,3,4,6,7,8]]]],[1,{"0":0,"1":1,"2":1},[[0,8,[0,2,3,4,6,7,8]],[1,9,[0,1,5,8,9]],[1,8,[0,1,5,8,9]],[0,9,[0,2,3,4,6,7,8]]]],[1,{"0":1,"1":0,"2":0},[[0,8,[0,2,3,4,6,7,8]],[1,9,[0,1,5,8,9]],[1,8,[0,1,5,8,9]],[0,9,[0,2,3,4,6,7,8]]]],[1,{"0":1,"1":0,"2":1},[[0,8,[0,2,3,4,6,7,8]],[1,9,[0,1,5,8,9]],[1,8,[0,1,5,8,9]],[0,9,[0,2,3,4,6,7,8]]]],[1,{"0":1,"1":1,"2":0},[[0,8,[0,2,3,4,6,7,8]],[1,9,[0,1,5,8,9]],[1,8,[0,1,5,8,9]],[0,9,[0,2,3,4,6,7,8]]]],[1,{"0":1,"1":1,"2":1},[[0,8,[0,2,3,4,6,7,8]],[1,9,[0,1,5,8,9]],[1,8,[0,1,5,8,9]],[0,9,[0,2,3,4,6,7,8]]]]]],["Opaque","111111111111111","","",{"0":0,"1":0,"2":0},[[1,{"0":0,"1":0,"2":0},[[0,8,[0,2,3,4,6,7,8]],[1,9,[0,1,5,8,9]],[1,8,[0,1,5,8,9]],[0,9,[0,2,3,4,6,7,8]]]],[1,{"0":0,"1":0,"2":1},[[0,8,[0,2,3,4,6,7,8]],[1,9,[0,1,5,8,9]],[1,8,[0,1,5,8,9]],[0,9,[0,2,3,4,6,7,8]]]],[1,{"0":0,"1":1,"2":0},[[0,8,[0,2,3,4,6,7,8]],[1,9,[0,1,5,8,9]],[1,8,[0,1,5,8,9]],[0,9,[0,2,3,4,6,7,8]]]],[1,{"0":0,"1":1,"2":1},[[0,8,[0,2,3,4,6,7,8]],[1,9,[0,1,5,8,9]],[1,8,[0,1,5,8,9]],[0,9,[0,2,3,4,6,7,8]]]],[1,{"0":1,"1":0,"2":0},[[0,8,[0,2,3,4,6,7,8]],[1,9,[0,1,5,8,9]],[1,8,[0,1,5,8,9]],[0,9,[0,2,3,4,6,7,8]]]],[1,{"0":1,"1":0,"2":1},[[0,8,[0,2,3,4,6,7,8]],[1,9,[0,1,5,8,9]],[1,8,[0,1,5,8,9]],[0,9,[0,2,3,4,6,7,8]]]],[1,{"0":1,"1":1,"2":0},[[0,8,[0,2,3,4,6,7,8]],[1,9,[0,1,5,8,9]],[1,8,[0,1,5,8,9]],[0,9,[0,2,3,4,6,7,8]]]],[1,{"0":1,"1":1,"2":1},[[0,8,[0,2,3,4,6,7,8]],[1,9,[0,1,5,8,9]],[1,8,[0,1,5,8,9]],[0,9,[0,2,3,4,6,7,8]]]]]],["Transparent","111111111111111","","",{"0":0,"1":0,"2":0},[[1,{"0":0,"1":0,"2":0},[[0,8,[0,2,3,4,6,7,8]],[1,9,[0,1,5,8,9]],[1,8,[0,1,5,8,9]],[0,9,[0,2,3,4,6,7,8]]]],[1,{"0":0,"1":0,"2":1},[[0,8,[0,2,3,4,6,7,8]],[1,9,[0,1,5,8,9]],[1,8,[0,1,5,8,9]],[0,9,[0,2,3,4,6,7,8]]]],[1,{"0":0,"1":1,"2":0},[[0,8,[0,2,3,4,6,7,8]],[1,9,[0,1,5,8,9]],[1,8,[0,1,5,8,9]],[0,9,[0,2,3,4,6,7,8]]]],[1,{"0":0,"1":1,"2":1},[[0,8,[0,2,3,4,6,7,8]],[1,9,[0,1,5,8,9]],[1,8,[0,1,5,8,9]],[0,9,[0,2,3,4,6,7,8]]]],[1,{"0":1,"1":0,"2":0},[[0,8,[0,2,3,4,6,7,8]],[1,9,[0,1,5,8,9]],[1,8,[0,1,5,8,9]],[0,9,[0,2,3,4,6,7,8]]]],[1,{"0":1,"1":0,"2":1},[[0,8,[0,2,3,4,6,7,8]],[1,9,[0,1,5,8,9]],[1,8,[0,1,5,8,9]],[0,9,[0,2,3,4,6,7,8]]]],[1,{"0":1,"1":1,"2":0},[[0,8,[0,2,3,4,6,7,8]],[1,9,[0,1,5,8,9]],[1,8,[0,1,5,8,9]],[0,9,[0,2,3,4,6,7,8]]]],[1,{"0":1,"1":1,"2":1},[[0,8,[0,2,3,4,6,7,8]],[1,9,[0,1,5,8,9]],[1,8,[0,1,5,8,9]],[0,9,[0,2,3,4,6,7,8]]]]]]]]